build/lib/build/lib/build/lib/build/lib/build/lib/build/lib/build/lib/build/lib/build/lib/build/lib/build/lib/keyrings/gauth.py
build/lib/build/lib/build/lib/build/lib/build/lib/build/lib/build/lib/build/lib/build/lib/build/lib/keyrings/gauth.py
build/lib/build/lib/build/lib/build/lib/build/lib/build/lib/build/lib/build/lib/build/lib/keyrings/gauth.py
build/lib/build/lib/build/lib/build/lib/build/lib/build/lib/build/lib/build/lib/keyrings/gauth.py
build/lib/build/lib/build/lib/build/lib/build/lib/build/lib/build/lib/keyrings/gauth.py
build/lib/build/lib/build/lib/build/lib/build/lib/build/lib/keyrings/gauth.py
build/lib/build/lib/build/lib/build/lib/build/lib/keyrings/gauth.py
build/lib/build/lib/build/lib/build/lib/keyrings/gauth.py
build/lib/build/lib/build/lib/keyrings/gauth.py
build/lib/build/lib/keyrings/gauth.py
build/lib/keyrings/gauth.py
keyrings/gauth.py
keyrings.google_artifactregistry_auth_legacy-0.0.1.dist-info/LICENSE
keyrings.google_artifactregistry_auth_legacy-0.0.1.dist-info/METADATA
keyrings.google_artifactregistry_auth_legacy-0.0.1.dist-info/WHEEL
keyrings.google_artifactregistry_auth_legacy-0.0.1.dist-info/entry_points.txt
keyrings.google_artifactregistry_auth_legacy-0.0.1.dist-info/top_level.txt
keyrings.google_artifactregistry_auth_legacy-0.0.1.dist-info/RECORD
