Metadata-Version: 2.1
Name: keyrings.google-artifactregistry-auth-legacy
Version: 0.0.1
Summary: Keyring backend for Google Auth tokens
Home-page: https://github.com/GoogleCloudPlatform/artifact-registry-pypi-tools
Author: Megan Kuo
Author-email: megankuo@google.com
License: UNKNOWN
Platform: UNKNOWN
Classifier: Development Status :: 5 - Production/Stable
Classifier: Intended Audience :: Developers
Classifier: License :: OSI Approved :: Apache Software License
Classifier: Programming Language :: Python :: 3
Classifier: Programming Language :: Python :: 3 :: Only
Requires-Python: >=3.5
Requires-Dist: keyring
Requires-Dist: google-auth
Requires-Dist: requests
Provides-Extra: testing
Requires-Dist: pytest (!=3.7.3,>=3.5) ; extra == 'testing'
Requires-Dist: pytest-checkdocs (>=1.2.3) ; extra == 'testing'
Requires-Dist: pytest-flake8 ; extra == 'testing'
Requires-Dist: pytest-cov ; extra == 'testing'
Requires-Dist: pytest-black (>=0.3.7) ; (platform_python_implementation != "PyPy") and extra == 'testing'
Requires-Dist: pytest-mypy ; (platform_python_implementation != "PyPy") and extra == 'testing'
